pyluno/__init__.py
pyluno/accounts.py
pyluno/api.py
pyluno/market.py
pyluno/meta.py
pyluno/orders.py
pyluno/quotes.py
pyluno/receive.py
pyluno/utils.py
pyluno/withdrawal.py
pyluno-0.3.0.data/scripts/demo.py
pyluno-0.3.0.dist-info/DESCRIPTION.rst
pyluno-0.3.0.dist-info/METADATA
pyluno-0.3.0.dist-info/RECORD
pyluno-0.3.0.dist-info/WHEEL
pyluno-0.3.0.dist-info/metadata.json
pyluno-0.3.0.dist-info/top_level.txt
